MANIFEST.in
README.md
keplergl-jupyter.json
pyproject.toml
setup.cfg
setup.py
keplergl/__init__.py
keplergl/_version.py
keplergl/keplergl.py
keplergl-jupyter/labextension/package.json
keplergl-jupyter/labextension/static/100.f5a4870c817c6e7a5e21.js
keplergl-jupyter/labextension/static/1090.c7fd951f21a541ab1254.js
keplergl-jupyter/labextension/static/1090.c7fd951f21a541ab1254.js.LICENSE.txt
keplergl-jupyter/labextension/static/1146.84cd8c9b357b565130f4.js
keplergl-jupyter/labextension/static/1452.0b14f0c4eea4c5e6ede8.js
keplergl-jupyter/labextension/static/16.280bbe55b351f22305bb.js
keplergl-jupyter/labextension/static/1602.051f73d4bfb767d9d3de.js
keplergl-jupyter/labextension/static/1746.cca55b07b119416ca9d5.js
keplergl-jupyter/labextension/static/1780.e171cd9aad45ce836147.js
keplergl-jupyter/labextension/static/2189.59a372b1568eab543777.js
keplergl-jupyter/labextension/static/2473.0a775334966c9bbe95e2.js
keplergl-jupyter/labextension/static/2622.39924b018040c9fd8f3f.js
keplergl-jupyter/labextension/static/2622.39924b018040c9fd8f3f.js.LICENSE.txt
keplergl-jupyter/labextension/static/2860.01f111211426a7ac4f84.js
keplergl-jupyter/labextension/static/3180.909e74bd6527c02502a4.js
keplergl-jupyter/labextension/static/3180.909e74bd6527c02502a4.js.LICENSE.txt
keplergl-jupyter/labextension/static/3225.a0960dfe7fcab44474d5.js
keplergl-jupyter/labextension/static/3315.aacc4a09d039bae6ca01.js
keplergl-jupyter/labextension/static/3607.7d5c076089aaa91aeffc.js
keplergl-jupyter/labextension/static/3848.6b60e5934a69d23b43a7.js
keplergl-jupyter/labextension/static/4306.b828a8493307f51ae591.js
keplergl-jupyter/labextension/static/4331.d86b7b6af53d14a46911.js
keplergl-jupyter/labextension/static/4331.d86b7b6af53d14a46911.js.LICENSE.txt
keplergl-jupyter/labextension/static/4479.b19a27e53e21cdb5c047.js
keplergl-jupyter/labextension/static/4581.343b7c5313a6929ee33a.js
keplergl-jupyter/labextension/static/4581.343b7c5313a6929ee33a.js.LICENSE.txt
keplergl.egg-info/PKG-INFO
keplergl.egg-info/SOURCES.txt
keplergl.egg-info/dependency_links.txt
keplergl.egg-info/not-zip-safe
keplergl.egg-info/requires.txt
keplergl.egg-info/top_level.txt
