Metadata-Version: 2.2
Name: keplergl
Version: 0.3.7
Summary: This is a simple jupyter widget for kepler.gl, an advanced geospatial visualization tool, to render large-scale interactive maps.
Home-page: https://github.com/keplergl/kepler.gl/tree/master/bindings/kepler.gl-jupyter
Author: Shan He
Author-email: shan@uber.com
Keywords: ipython,jupyter,widgets,geospatial,visualization,webGL
Classifier: Development Status :: 4 - Beta
Classifier: Framework :: IPython
Classifier: Intended Audience :: Developers
Classifier: Intended Audience :: Science/Research
Classifier: Topic :: Multimedia :: Graphics
Classifier: Programming Language :: Python :: 2
Classifier: Programming Language :: Python :: 3.6
Classifier: Programming Language :: Python :: 3.7
Classifier: Programming Language :: Python :: 3.8
Classifier: Programming Language :: Python :: 3.9
Classifier: Programming Language :: Python :: 3.10
Classifier: Programming Language :: Python :: 3.11
Classifier: Programming Language :: Python :: 3.12
Requires-Dist: ipywidgets>=8.1.5
Requires-Dist: traittypes>=0.2.1
Requires-Dist: traitlets>=4.3.2
Requires-Dist: geopandas>=0.14.3
Requires-Dist: Shapely>=1.6.4.post2
Requires-Dist: jupyter_packaging>=0.12.3
Requires-Dist: jupyter>=1.0.0
Requires-Dist: jupyterlab>=4.1.6
Requires-Dist: notebook>=6.0.1
Requires-Dist: pyarrow>=16.0.0
Requires-Dist: geoarrow-pyarrow>=0.1.2
Requires-Dist: geoarrow-pandas>=0.1.1
Dynamic: author
Dynamic: author-email
Dynamic: classifier
Dynamic: description
Dynamic: home-page
Dynamic: keywords
Dynamic: requires-dist
Dynamic: summary
